fbiradio/__init__.py
fbiradio-0.0.2.data/scripts/fbiplaying
fbiradio-0.0.2.dist-info/LICENSE
fbiradio-0.0.2.dist-info/METADATA
fbiradio-0.0.2.dist-info/WHEEL
fbiradio-0.0.2.dist-info/top_level.txt
fbiradio-0.0.2.dist-info/RECORD
