Metadata-Version: 2.1
Name: fbiradio
Version: 0.0.2
Summary: Find currently playing track on FBi Radio
Home-page: https://github.com/cchristiansen/fbiradio
Author: Christian Christiansen
Author-email: christian.l.christiansen@gmail.com
License: UNKNOWN
Platform: UNKNOWN
Classifier: Programming Language :: Python :: 3
Classifier: License :: OSI Approved :: GNU Affero General Public License v3 or later (AGPLv3+)
Classifier: Operating System :: OS Independent
Classifier: Topic :: Multimedia :: Sound/Audio
Requires-Python: >=3.6
Requires-Dist: beautifulsoup4
Requires-Dist: requests
